htmldocx/__init__.py
htmldocx/h2d.py
htmldocx-0.0.6.dist-info/LICENSE
htmldocx-0.0.6.dist-info/METADATA
htmldocx-0.0.6.dist-info/WHEEL
htmldocx-0.0.6.dist-info/top_level.txt
htmldocx-0.0.6.dist-info/RECORD
