Metadata-Version: 2.1
Name: htmldocx
Version: 0.0.6
Summary: Convert html to docx
Home-page: https://github.com/pqzx/html2docx
Author: pqzx
Author-email: jc3664@gmail.com
License: UNKNOWN
Project-URL: Bug Tracker, https://github.com/pqzx/html2docx/issues
Platform: UNKNOWN
Classifier: Programming Language :: Python :: 3
Classifier: License :: OSI Approved :: MIT License
Classifier: Operating System :: OS Independent
Requires-Python: >=3.6
License-File: LICENSE
